[
  {
    "monsterName": "Beelzebub",
    "location": "Monster Avenue",
    "faction": "Margaretha",
    "level": 1,
    "totalHealth": 2175,
    "totalAttack": 500,
    "totalDefense": 510,
    "expDropped": 50,
    "iuraDropped": 10
  },
  {
    "monsterName": "Dead Knight",
    "location": "Wilderness",
    "faction": "Margaretha",
    "level": 1,
    "totalHealth": 2175,
    "totalAttack": 500,
    "totalDefense": 510,
    "expDropped": 50,
    "iuraDropped": 10
  },
  {
    "monsterName": "Elder",
    "location": "Wilderness",
    "faction": "Margaretha",
    "level": 1,
    "totalHealth": 2175,
    "totalAttack": 500,
    "totalDefense": 510,
    "expDropped": 50,
    "iuraDropped": 10
  },
  {
    "monsterName": "Cyclops",
    "location": "Wilderness",
    "faction": "Margaretha",
    "level": 1,
    "totalHealth": 2175,
    "totalAttack": 500,
    "totalDefense": 510,
    "expDropped": 50,
    "iuraDropped": 10
  },
  {
    "monsterName": "Chimera",
    "location": "Monster Avenue",
    "faction": "Cerberon",
    "level": 1,
    "totalHealth": 2175,
    "totalAttack": 500,
    "totalDefense": 510,
    "expDropped": 50,
    "iuraDropped": 10
  },
  {
    "monsterName": "Wyvern",
    "location": "Monster Avenue",
    "faction": "Cerberon",
    "level": 1,
    "totalHealth": 2175,
    "totalAttack": 500,
    "totalDefense": 510,
    "expDropped": 50,
    "iuraDropped": 10
  },
  {
    "monsterName": "Kraken",
    "location": "Monster Avenue",
    "faction": "Cerberon",
    "level": 1,
    "totalHealth": 2175,
    "totalAttack": 500,
    "totalDefense": 510,
    "expDropped": 50,
    "iuraDropped": 10
  },
  {
    "monsterName": "Manticore",
    "location": "Monster Avenue",
    "faction": "Cerberon",
    "level": 1,
    "totalHealth": 2175,
    "totalAttack": 500,
    "totalDefense": 510,
    "expDropped": 50,
    "iuraDropped": 10
  },
  {
    "monsterName": "Cockatrice",
    "location": "Monster Avenue",
    "faction": "Cerberon",
    "level": 1,
    "totalHealth": 2175,
    "totalAttack": 500,
    "totalDefense": 510,
    "expDropped": 50,
    "iuraDropped": 10
  },
  {
    "monsterName": "Harpy",
    "location": "Monster Avenue",
    "faction": "Cerberon",
    "level": 1,
    "totalHealth": 2175,
    "totalAttack": 500,
    "totalDefense": 510,
    "expDropped": 50,
    "iuraDropped": 10
  },
  {
    "monsterName": "Necronomicon",
    "location": "Monster Avenue",
    "faction": "Margaretha",
    "level": 2,
    "totalHealth": 6375,
    "totalAttack": 1613,
    "totalDefense": 750,
    "expDropped": 50,
    "iuraDropped": 10
  },
  {
    "monsterName": "Minotaur",
    "location": "Monster Avenue",
    "faction": "Cerberon",
    "level": 2,
    "totalHealth": 6375,
    "totalAttack": 1613,
    "totalDefense": 750,
    "expDropped": 50,
    "iuraDropped": 10
  },
  {
    "monsterName": "Hydra",
    "location": "Wilderness",
    "faction": "Margaretha",
    "level": 2,
    "totalHealth": 6375,
    "totalAttack": 1613,
    "totalDefense": 750,
    "expDropped": 50,
    "iuraDropped": 10
  },
  {
    "monsterName": "Valraven",
    "location": "Wilderness",
    "faction": "Margaretha",
    "level": 2,
    "totalHealth": 6375,
    "totalAttack": 1613,
    "totalDefense": 750,
    "expDropped": 50,
    "iuraDropped": 10
  },
  {
    "monsterName": "Gorgon",
    "location": "Wilderness",
    "faction": "Cerberon",
    "level": 2,
    "totalHealth": 6375,
    "totalAttack": 1613,
    "totalDefense": 750,
    "expDropped": 50,
    "iuraDropped": 10
  },
  {
    "monsterName": "Basilisk",
    "location": "Wilderness",
    "faction": "Cerberon",
    "level": 2,
    "totalHealth": 6375,
    "totalAttack": 1613,
    "totalDefense": 750,
    "expDropped": 50,
    "iuraDropped": 10
  },
  {
    "monsterName": "Wraith",
    "location": "Wilderness",
    "faction": "Cerberon",
    "level": 2,
    "totalHealth": 6375,
    "totalAttack": 1613,
    "totalDefense": 750,
    "expDropped": 50,
    "iuraDropped": 10
  },
  {
    "monsterName": "Goblin",
    "location": "Wilderness",
    "faction": "Cerberon",
    "level": 2,
    "totalHealth": 6375,
    "totalAttack": 1613,
    "totalDefense": 750,
    "expDropped": 50,
    "iuraDropped": 10
  },
  {
    "monsterName": "Ogre",
    "location": "Wilderness",
    "faction": "Cerberon",
    "level": 2,
    "totalHealth": 6375,
    "totalAttack": 1613,
    "totalDefense": 750,
    "expDropped": 50,
    "iuraDropped": 10
  },
  {
    "monsterName": "Zombie",
    "location": "Wilderness",
    "faction": "Cerberon",
    "level": 2,
    "totalHealth": 6375,
    "totalAttack": 1613,
    "totalDefense": 750,
    "expDropped": 50,
    "iuraDropped": 10
  }
]
